mccstyle/__init__.py
mccstyle-0.0.1.dist-info/METADATA
mccstyle-0.0.1.dist-info/WHEEL
mccstyle-0.0.1.dist-info/top_level.txt
mccstyle-0.0.1.dist-info/RECORD
