Metadata-Version: 2.1
Name: mccstyle
Version: 0.0.1
Summary: Styling for Muon Collider Detector ROOT plots.
Home-page: https://github.com/kkrizka/mccstyle
Author: Karol Krizka
Author-email: kkrizka@gmail.com
Classifier: Programming Language :: Python :: 3
Classifier: License :: OSI Approved :: GNU General Public License v3 (GPLv3)
Classifier: Operating System :: OS Independent
